Flamoon-0.1.11.dist-info/METADATA
Flamoon-0.1.11.dist-info/RECORD
Flamoon-0.1.11.dist-info/WHEEL
Flamoon-0.1.11.dist-info/entry_points.txt
Flamoon-0.1.11.dist-info/top_level.txt
flamoon/__init__.py
flamoon/app.py
flamoon/cli.py
flamoon/config.py
flamoon/template_app/.env
flamoon/template_app/config.py
flamoon/template_app/manage.py
flamoon/template_app/app/__init__.py
flamoon/template_app/app/email.py
flamoon/template_app/app/extensions.py
flamoon/template_app/app/ex/__init__.py
flamoon/template_app/app/ex/data.py
flamoon/template_app/app/ex/forms.py
flamoon/template_app/app/ex/views.py
flamoon/template_app/app/ex/templates/ex.html
flamoon/template_app/app/models/user.py
flamoon/template_app/app/static/img/favicon.ico
flamoon/template_app/app/templates/base.html
flamoon/template_app/tests/app/test_app.py
flamoon/template_app/tests/client/test_client.py
