Metadata-Version: 2.1
Name: Flamoon
Version: 0.1.11
Summary: Надстройка над Flask, для быстрой и удобной web-разработки.
Home-page: https://github.com/volitilov/flamoon
Author: volitilov
Author-email: volitilov@gmail.com
License: MIT
Platform: UNKNOWN
Classifier: Intended Audience :: Developers
Classifier: Natural Language :: Russian
Classifier: Development Status :: 4 - Beta
Classifier: License :: OSI Approved :: MIT License
Classifier: Programming Language :: Python :: 3.5
Classifier: Topic :: Software Development :: Libraries :: Application Frameworks
Classifier: Operating System :: POSIX :: Linux
Requires-Dist: Flask (==1.0.2)
Requires-Dist: Flask-Login (==0.4.1)
Requires-Dist: Flask-Mail (==0.9.1)
Requires-Dist: python-dotenv (==0.8.2)
Requires-Dist: Flask-SQLAlchemy (==2.3.2)
Requires-Dist: Flask-Migrate (==2.1.1)
Requires-Dist: psycopg2 (==2.7.4)
Requires-Dist: psycopg2-binary (==2.7.5)
